<?xml version="1.0" encoding="UTF-8"?>
<!DOCTYPE mapper PUBLIC "-//mybatis.org//DTD Mapper 3.0//EN" "http://mybatis.org/dtd/mybatis-3-mapper.dtd">
<mapper namespace="com.autolight.dao.OrderofrepairMapper">
  <resultMap id="BaseResultMap" type="com.autolight.entity.Orderofrepair">
    <!--
      WARNING - @mbg.generated
      This element is automatically generated by MyBatis Generator, do not modify.
      This element was generated on Mon Mar 30 16:36:45 CST 2020.
    -->
    <id column="orderofrepair_id" jdbcType="INTEGER" property="orderofrepair_id" />
    <result column="room_name" jdbcType="VARCHAR" property="room_name" />
    <result column="user_id" jdbcType="INTEGER" property="user_id" />
    <result column="user_name" jdbcType="VARCHAR" property="user_name" />
    <result column="orderofrepair_text" jdbcType="VARCHAR" property="orderofrepair_text" />
    <result column="orderofrepair_time" jdbcType="TIMESTAMP" property="orderofrepair_time" />
  </resultMap>
  <sql id="Base_Column_List">
    <!--
      WARNING - @mbg.generated
      This element is automatically generated by MyBatis Generator, do not modify.
      This element was generated on Mon Mar 30 16:36:45 CST 2020.
    -->
    orderofrepair_id, room_name, user_id, user_name, orderofrepair_text, orderofrepair_time
  </sql>
  <select id="selectByPrimaryKey" parameterType="java.lang.Integer" resultMap="BaseResultMap">
    <!--
      WARNING - @mbg.generated
      This element is automatically generated by MyBatis Generator, do not modify.
      This element was generated on Mon Mar 30 16:36:45 CST 2020.
    -->
    select 
    <include refid="Base_Column_List" />
    from tb_orderofrepair
    where orderofrepair_id = #{orderofrepair_id,jdbcType=INTEGER}
  </select>
  <delete id="deleteByPrimaryKey" parameterType="java.lang.Integer">
    <!--
      WARNING - @mbg.generated
      This element is automatically generated by MyBatis Generator, do not modify.
      This element was generated on Mon Mar 30 16:36:45 CST 2020.
    -->
    delete from tb_orderofrepair
    where orderofrepair_id = #{orderofrepair_id,jdbcType=INTEGER}
  </delete>
  <insert id="insert" parameterType="com.autolight.entity.Orderofrepair">
    <!--
      WARNING - @mbg.generated
      This element is automatically generated by MyBatis Generator, do not modify.
      This element was generated on Mon Mar 30 16:36:45 CST 2020.
    -->
    insert into tb_orderofrepair (orderofrepair_id, room_name, user_id, 
      user_name, orderofrepair_text, orderofrepair_time
      )
    values (#{orderofrepair_id,jdbcType=INTEGER}, #{room_name,jdbcType=VARCHAR}, #{user_id,jdbcType=INTEGER}, 
      #{user_name,jdbcType=VARCHAR}, #{orderofrepair_text,jdbcType=VARCHAR}, #{orderofrepair_time,jdbcType=TIMESTAMP}
      )
  </insert>
  <insert id="insertSelective" parameterType="com.autolight.entity.Orderofrepair">
    <!--
      WARNING - @mbg.generated
      This element is automatically generated by MyBatis Generator, do not modify.
      This element was generated on Mon Mar 30 16:36:45 CST 2020.
    -->
    insert into tb_orderofrepair
    <trim prefix="(" suffix=")" suffixOverrides=",">
      <if test="orderofrepair_id != null">
        orderofrepair_id,
      </if>
      <if test="room_name != null">
        room_name,
      </if>
      <if test="user_id != null">
        user_id,
      </if>
      <if test="user_name != null">
        user_name,
      </if>
      <if test="orderofrepair_text != null">
        orderofrepair_text,
      </if>
      <if test="orderofrepair_time != null">
        orderofrepair_time,
      </if>
    </trim>
    <trim prefix="values (" suffix=")" suffixOverrides=",">
      <if test="orderofrepair_id != null">
        #{orderofrepair_id,jdbcType=INTEGER},
      </if>
      <if test="room_name != null">
        #{room_name,jdbcType=VARCHAR},
      </if>
      <if test="user_id != null">
        #{user_id,jdbcType=INTEGER},
      </if>
      <if test="user_name != null">
        #{user_name,jdbcType=VARCHAR},
      </if>
      <if test="orderofrepair_text != null">
        #{orderofrepair_text,jdbcType=VARCHAR},
      </if>
      <if test="orderofrepair_time != null">
        #{orderofrepair_time,jdbcType=TIMESTAMP},
      </if>
    </trim>
  </insert>
  <update id="updateByPrimaryKeySelective" parameterType="com.autolight.entity.Orderofrepair">
    <!--
      WARNING - @mbg.generated
      This element is automatically generated by MyBatis Generator, do not modify.
      This element was generated on Mon Mar 30 16:36:45 CST 2020.
    -->
    update tb_orderofrepair
    <set>
      <if test="room_name != null">
        room_name = #{room_name,jdbcType=VARCHAR},
      </if>
      <if test="user_id != null">
        user_id = #{user_id,jdbcType=INTEGER},
      </if>
      <if test="user_name != null">
        user_name = #{user_name,jdbcType=VARCHAR},
      </if>
      <if test="orderofrepair_text != null">
        orderofrepair_text = #{orderofrepair_text,jdbcType=VARCHAR},
      </if>
      <if test="orderofrepair_time != null">
        orderofrepair_time = #{orderofrepair_time,jdbcType=TIMESTAMP},
      </if>
    </set>
    where orderofrepair_id = #{orderofrepair_id,jdbcType=INTEGER}
  </update>
  <update id="updateByPrimaryKey" parameterType="com.autolight.entity.Orderofrepair">
    <!--
      WARNING - @mbg.generated
      This element is automatically generated by MyBatis Generator, do not modify.
      This element was generated on Mon Mar 30 16:36:45 CST 2020.
    -->
    update tb_orderofrepair
    set room_name = #{room_name,jdbcType=VARCHAR},
      user_id = #{user_id,jdbcType=INTEGER},
      user_name = #{user_name,jdbcType=VARCHAR},
      orderofrepair_text = #{orderofrepair_text,jdbcType=VARCHAR},
      orderofrepair_time = #{orderofrepair_time,jdbcType=TIMESTAMP}
    where orderofrepair_id = #{orderofrepair_id,jdbcType=INTEGER}
  </update>

	<select id="findOrderofrepairAll" resultType="com.autolight.entity.Orderofrepair">
		select
		orderofrepair_id,
		room_name,
		user_id,
		user_name,
		orderofrepair_text,
	    orderofrepair_time
		from
		autolightcontrol.tb_orderofrepair
	</select>
	<select id="findOrderofrepairByID" parameterType="int" resultType="com.autolight.entity.Orderofrepair">
		select
		orderofrepair_id,
		room_name,
		user_id,
		user_name,
		orderofrepair_text,
		orderofrepair_time
		from
		autolightcontrol.tb_orderofrepair
		where
		orderofrepair_id = #{value}
	</select>
	
	<insert id="saveOrderofrepair" parameterType="com.autolight.entity.Orderofrepair">
		INSERT INTO autolightcontrol.tb_orderofrepair
		(room_name, user_id,user_name,orderofrepair_text,orderofrepair_time)
		VALUES
		(#{room_name},#{user_id},#{user_name},#{orderofrepair_text},now())
	</insert>
	<update id="updateOrderofrepair" parameterType="com.autolight.entity.Orderofrepair">
		UPDATE autolightcontrol.tb_orderofrepair
		SET
		room_name = #{room_name},
		user_id = #{user_id},
		user_name = #{user_name},
		orderofrepair_text = #{orderofrepair_text},
		orderofrepair_time = now()
		WHERE orderofrepair_id = #{orderofrepair_id}
	</update>
	<delete id="deleteOrderofrepair" parameterType="Integer[]">
		delete from autolightcontrol.tb_orderofrepair
		<where>
			orderofrepair_id
			<foreach close=")" collection="array" item="id" open="in (" separator=",">
				#{id}
			</foreach>
		</where>
	</delete>


</mapper>